lb/__init__.py
lb/_version.py
lb/lb.py
lb/py.typed
little_bank-0.1.0.dist-info/licenses/LICENSE
little_bank-0.1.0.dist-info/METADATA
little_bank-0.1.0.dist-info/WHEEL
little_bank-0.1.0.dist-info/top_level.txt
little_bank-0.1.0.dist-info/RECORD
