Metadata-Version: 2.4
Name: little-bank
Version: 0.1.0
Summary:  Double book-keeping transaction framework
Author-email: Anton Agestam <git@antonagestam.se>
License-Expression: BSD-3-Clause
Project-URL: Source Repository, https://github.com/antonagestam/little-bank/
Project-URL: Bug Tracker, https://github.com/antonagestam/little-bank/issues
Classifier: Intended Audience :: Developers
Classifier: Operating System :: OS Independent
Classifier: Programming Language :: Python
Classifier: Programming Language :: Python :: 3
Classifier: Programming Language :: Python :: 3 :: Only
Classifier: Programming Language :: Python :: 3.13
Classifier: Development Status :: 4 - Beta
Classifier: Typing :: Typed
Requires-Python: >=3.13
License-File: LICENSE
Provides-Extra: test
Requires-Dist: mypy; extra == "test"
Requires-Dist: pytest; extra == "test"
Requires-Dist: pytest-mypy-plugins; extra == "test"
Requires-Dist: pytest-random-order; extra == "test"
Requires-Dist: coverage; extra == "test"
Requires-Dist: phantom-types; extra == "test"
Dynamic: license-file
